pyfrpc-0.2.13.dist-info/entry_points.txt
pyfrpc-0.2.13.dist-info/WHEEL
pyfrpc-0.2.13.dist-info/LICENSE.txt
pyfrpc-0.2.13.dist-info/METADATA
pyfrpc-0.2.13.dist-info/top_level.txt
pyfrpc-0.2.13.dist-info/RECORD
pyfrpc/netcat.py
pyfrpc/client.py
pyfrpc/_coding_base_c.cpython-311-x86_64-linux-gnu.so
pyfrpc/__main__.py
pyfrpc/_coding_base_py.py
pyfrpc/_coding_base_c.pyx
pyfrpc/__init__.py
pyfrpc/coding.py
pyfrpc/models.py
pyfrpc/asyncclient.py
