Metadata-Version: 2.1
Name: pyfrpc
Version: 0.2.13
Summary: Python implementation of fastrpc protocol
Author: Vladimir Burian
Project-URL: Homepage, https://gitlab.com/vladaburian/pyfrpc
Keywords: frpc,fastrpc
Classifier: License :: OSI Approved :: MIT License
Classifier: Programming Language :: Python :: 3
Classifier: Programming Language :: Python :: 3.9
Classifier: Programming Language :: Python :: 3.10
Classifier: Programming Language :: Python :: 3.11
Classifier: Programming Language :: Python :: 3.12
Classifier: Programming Language :: Python :: 3.13
License-File: LICENSE.txt
Requires-Dist: requests
Provides-Extra: nc
Requires-Dist: ipython; extra == "nc"
Provides-Extra: async
Requires-Dist: aiohttp; extra == "async"
